CHANGES.txt
README.txt
bootstrap.py
buildout.cfg
setup.py
src/zope/__init__.py
src/zope.app.xmlrpcintrospection.egg-info/PKG-INFO
src/zope.app.xmlrpcintrospection.egg-info/SOURCES.txt
src/zope.app.xmlrpcintrospection.egg-info/dependency_links.txt
src/zope.app.xmlrpcintrospection.egg-info/namespace_packages.txt
src/zope.app.xmlrpcintrospection.egg-info/not-zip-safe
src/zope.app.xmlrpcintrospection.egg-info/requires.txt
src/zope.app.xmlrpcintrospection.egg-info/top_level.txt
src/zope/app/__init__.py
src/zope/app/xmlrpcintrospection/README.txt
src/zope/app/xmlrpcintrospection/SETUP.cfg
src/zope/app/xmlrpcintrospection/__init__.py
src/zope/app/xmlrpcintrospection/configure.zcml
src/zope/app/xmlrpcintrospection/ftesting.zcml
src/zope/app/xmlrpcintrospection/ftests.py
src/zope/app/xmlrpcintrospection/testing.py
src/zope/app/xmlrpcintrospection/xmlintrospection-configure.zcml
src/zope/app/xmlrpcintrospection/xmlrpcintrospection.py
src/zope/app/xmlrpcintrospection/tests/__init__.py
src/zope/app/xmlrpcintrospection/tests/test_functional.py
src/zope/app/xmlrpcintrospection/tests/test_xmlrpcintrospection.py