Metadata-Version: 1.0
Name: zope.app.xmlrpcintrospection
Version: 3.5.1
Summary: XML-RPC Method Introspection Support for Zope 3
Home-page: http://pypi.python.org/pypi/zope.app.xmlrpcintrospection
Author: Zope Corporation and Contributors
Author-email: zope-dev@zope.org
License: ZPL 2.1
Keywords: zope3 xmlrpcintrospection site local component
Platform: UNKNOWN
Classifier: Development Status :: 5 - Production/Stable
Classifier: Environment :: Web Environment
Classifier: Intended Audience :: Developers
Classifier: License :: OSI Approved :: Zope Public License
Classifier: Programming Language :: Python
Classifier: Natural Language :: English
Classifier: Operating System :: OS Independent
Classifier: Topic :: Internet :: WWW/HTTP
Classifier: Framework :: Zope3
